{"Car owners": [{"first_name": "Myrtie", "last_name": "Yakobovicz", "car": "Land Rover"}, {"first_name": "Gerhardine", "last_name": "Corsan", "car": "GMC"}, {"first_name": "Ursa", "last_name": "Linklater", "car": "Jaguar"}, {"first_name": "Alyda", "last_name": "Duffin", "car": "Austin"}, {"first_name": "Anton", "last_name": "Woolrich", "car": "Lincoln"}, {"first_name": "Belvia", "last_name": "Cosser", "car": "Honda"}, {"first_name": "Janina", "last_name": "Melding", "car": "Lincoln"}, {"first_name": "Pryce", "last_name": "Olivo", "car": "Toyota"}, {"first_name": "Fabe", "last_name": "Heimes", "car": "Volvo"}, {"first_name": "Otha", "last_name": "Hachette", "car": "Mercedes-Benz"}]}